flake8_logging/__init__.py
flake8_logging/py.typed
flake8_logging-1.8.0.dist-info/licenses/LICENSE
flake8_logging-1.8.0.dist-info/METADATA
flake8_logging-1.8.0.dist-info/WHEEL
flake8_logging-1.8.0.dist-info/entry_points.txt
flake8_logging-1.8.0.dist-info/top_level.txt
flake8_logging-1.8.0.dist-info/RECORD
